{"status":"success","data":{"resultType":"vector","result":[{"metric":{"__name__":"ALERTS","alertname":"AlertmanagerReceiversNotConfigured","alertstate":"firing","namespace":"openshift-monitoring","severity":"warning"},"value":[1686068518.929,"1"]},{"metric":{"__name__":"ALERTS","alertname":"ClusterNotUpgradeable","alertstate":"firing","condition":"Upgradeable","endpoint":"metrics","name":"version","namespace":"openshift-cluster-version","severity":"info"},"value":[1686068518.929,"1"]},{"metric":{"__name__":"ALERTS","alertname":"InsightsRecommendationActive","alertstate":"firing","container":"insights-operator","description":"Prometheus metrics data will be lost when the Prometheus pod is restarted or recreated","endpoint":"https","info_link":"https://console.redhat.com/openshift/insights/advisor/clusters/dcb4c20d-59aa-409e-a9ce-5e144d1eb700?first=ccx_rules_ocp.external.rules.empty_prometheus_db_volume|PROMETHEUS_DB_VOLUME_IS_EMPTY","instance":"10.128.0.78:8443","job":"metrics","namespace":"openshift-insights","pod":"insights-operator-865f99b9c7-hmrdb","service":"metrics","severity":"info","total_risk":"Low"},"value":[1686068518.929,"1"]},{"metric":{"__name__":"ALERTS","alertname":"SimpleContentAccessNotAvailable","alertstate":"firing","condition":"SCAAvailable","endpoint":"metrics","name":"insights","namespace":"openshift-insights","reason":"NotFound","severity":"info"},"value":[1686068518.929,"1"]},{"metric":{"__name__":"ALERTS","alertname":"UpdateAvailable","alertstate":"firing","channel":"stable-4.12","namespace":"openshift-cluster-version","severity":"info","upstream":"\u003cdefault\u003e"},"value":[1686068518.929,"1"]},{"metric":{"__name__":"ALERTS","alertname":"Watchdog","alertstate":"firing","namespace":"openshift-monitoring","severity":"none"},"value":[1686068518.929,"1"]},{"metric":{"__name__":"ALERTS","alertname":"etcdDatabaseHighFragmentationRatio","alertstate":"pending","endpoint":"etcd-metrics","instance":"10.0.193.153:9979","job":"etcd","namespace":"openshift-etcd","pod":"etcd-ip-10-0-193-153.ap-southeast-1.compute.internal","service":"etcd","severity":"warning"},"value":[1686068518.929,"1"]}]}}
